flip_evaluator-1.7.dist-info/RECORD
flip_evaluator-1.7.dist-info/WHEEL
flip_evaluator-1.7.dist-info/entry_points.txt
flip_evaluator-1.7.dist-info/METADATA
flip_evaluator-1.7.dist-info/licenses/LICENSE
flip_evaluator/nbflip.cpython-38-darwin.so
flip_evaluator/flip_python_api.py
flip_evaluator/__init__.py
