Metadata-Version: 2.1
Name: flip-evaluator
Version: 1.7
Summary: A Difference Evaluator for Alternating Images
Author: Pontus Ebelin, Tomas Akenine-Möller
Classifier: License :: OSI Approved :: BSD License
Project-URL: Homepage, https://github.com/nvlabs/flip
Requires-Python: >=3.8
